vecsim/__init__.py
vecsim/similarity_helpers.py
vecsim-0.0.62.dist-info/LICENSE
vecsim-0.0.62.dist-info/METADATA
vecsim-0.0.62.dist-info/WHEEL
vecsim-0.0.62.dist-info/top_level.txt
vecsim-0.0.62.dist-info/RECORD
