Metadata-Version: 2.1
Name: vecsim
Version: 0.0.62
Summary: Vector Similarity Search Engine
Home-page: https://github.com/argmaxml/vecsim
Author: ArgmaxML
Author-email: ugoren@argmax.ml
Keywords: vector-similarity,faiss,hnsw,redis,matching,ranking,elasticsearch,search,embedding
License-File: LICENSE
Requires-Dist: numpy >=1.21.2
Requires-Dist: pandas >=1.3.0
Requires-Dist: scikit-learn >=0.19.0
Provides-Extra: elasticsearch
Requires-Dist: elasticsearch >=8.5.0 ; extra == 'elasticsearch'
Provides-Extra: faiss
Requires-Dist: faiss-cpu >=1.7.1 ; extra == 'faiss'
Provides-Extra: pinecone
Requires-Dist: pinecone-client >=2.2.0 ; extra == 'pinecone'
Provides-Extra: postgres
Requires-Dist: psycopg2-binary ~=2.9.3 ; extra == 'postgres'
Requires-Dist: SQLAlchemy ~=1.3.22 ; extra == 'postgres'
Provides-Extra: redis
Requires-Dist: redis >=4.3.0 ; extra == 'redis'
